headless_kivy_pi/__init__.py
headless_kivy_pi/config.py
headless_kivy_pi/constants.py
headless_kivy_pi/display.py
headless_kivy_pi/fake.py
headless_kivy_pi/logger.py
headless_kivy_pi_pytest/__init__.py
headless_kivy_pi_pytest/fixtures/__init__.py
headless_kivy_pi_pytest/fixtures/snapshot.py
headless_kivy_pi_pytest/plugin.py
headless_kivy_pi-0.8.2.dist-info/LICENSE
headless_kivy_pi-0.8.2.dist-info/METADATA
headless_kivy_pi-0.8.2.dist-info/WHEEL
headless_kivy_pi-0.8.2.dist-info/RECORD
