Metadata-Version: 2.1
Name: headless-kivy-pi
Version: 0.8.2
Summary: Headless renderer for Kivy framework
Home-page: https://github.com/sassanh/headless-kivy-pi/
License: Apache-2.0
Keywords: kivy,headless,display,pytest
Author: Sassan Haradji
Author-email: sassanh@gmail.com
Requires-Python: >=3.11,<4.0
Classifier: License :: OSI Approved :: Apache Software License
Classifier: Programming Language :: Python :: 3
Classifier: Programming Language :: Python :: 3.11
Classifier: Programming Language :: Python :: 3.12
Provides-Extra: dev
Requires-Dist: adafruit-circuitpython-aw9523 (>=1.1.7,<2.0.0) ; platform_machine == "aarch64"
Requires-Dist: adafruit-circuitpython-rgb-display (>=3.11.0,<4.0.0) ; platform_machine == "aarch64"
Requires-Dist: kivy (>=2.2.1,<3.0.0)
Requires-Dist: numpy (>=1.24.2,<2.0.0)
Requires-Dist: poethepoet (>=0.24.2,<0.25.0) ; extra == "dev"
Requires-Dist: python-strtobool (>=1.0.0,<2.0.0)
Requires-Dist: screeninfo (>=0.8.1,<0.9.0) ; extra == "dev"
Requires-Dist: typing-extensions (>=4.8.0,<5.0.0)
Project-URL: Repository, https://github.com/sassanh/headless-kivy-pi/
